hasnainkk/__init__.py
hasnainkk/client.py
hasnainkk/filters.py
hasnainkk/handler.py
hasnainkk_07-1.0.0.dist-info/licenses/LICENSE
hasnainkk_07-1.0.0.dist-info/METADATA
hasnainkk_07-1.0.0.dist-info/WHEEL
hasnainkk_07-1.0.0.dist-info/top_level.txt
hasnainkk_07-1.0.0.dist-info/RECORD
